tinytext/__init__.py
tinytext/__main__.py
tinytext/_version.py
tinytext/cli.py
tinytext-4.1.0.dist-info/METADATA
tinytext-4.1.0.dist-info/WHEEL
tinytext-4.1.0.dist-info/entry_points.txt
tinytext-4.1.0.dist-info/licenses/LICENSE.txt
tinytext-4.1.0.dist-info/RECORD
