Metadata-Version: 2.4
Name: tinytext
Version: 4.1.0
Summary: A helpful converter to change any normal text into cuter tinier text
Project-URL: Changelog, https://github.com/hugovk/tinytext/releases
Project-URL: Homepage, https://github.com/hugovk/tinytext
Project-URL: Source, https://github.com/hugovk/tinytext
Author: Hugo van Kemenade
License-Expression: MIT
License-File: LICENSE.txt
Keywords: botally,cute text,generator,tiny text,tiny type
Classifier: Development Status :: 5 - Production/Stable
Classifier: Intended Audience :: Developers
Classifier: Natural Language :: English
Classifier: Programming Language :: Python :: 3 :: Only
Classifier: Programming Language :: Python :: 3.10
Classifier: Programming Language :: Python :: 3.11
Classifier: Programming Language :: Python :: 3.12
Classifier: Programming Language :: Python :: 3.13
Classifier: Programming Language :: Python :: 3.14
Classifier: Programming Language :: Python :: Implementation :: CPython
Classifier: Programming Language :: Python :: Implementation :: PyPy
Classifier: Topic :: Artistic Software
Classifier: Topic :: Text Processing
Requires-Python: >=3.10
Provides-Extra: tests
Requires-Dist: pytest; extra == 'tests'
Requires-Dist: pytest-cov; extra == 'tests'
